excel_slim-0.1.0.dist-info/METADATA
excel_slim-0.1.0.dist-info/WHEEL
excel_slim-0.1.0.dist-info/licenses/LICENSE
excel_slim/__init__.py
excel_slim/_native.cpython-311-darwin.so
excel_slim-0.1.0.dist-info/RECORD
