Metadata-Version: 2.4
Name: excel-slim
Version: 0.1.0
License-File: LICENSE
Summary: Slim Excel files safely with a Rust core
License: MIT OR Apache-2.0
Requires-Python: >=3.8
